auto_audio/__init__.py
auto_audio/api.py
auto_audio-0.0.5.dist-info/LICENSE
auto_audio-0.0.5.dist-info/METADATA
auto_audio-0.0.5.dist-info/WHEEL
auto_audio-0.0.5.dist-info/top_level.txt
auto_audio-0.0.5.dist-info/RECORD
