Metadata-Version: 2.1
Name: auto-audio
Version: 0.0.5
Summary: You can upload audio files to Air force program
Home-page: https://github.com/hanayong
Author: hanayong
License: UNKNOWN
Platform: UNKNOWN
Classifier: Programming Language :: Python :: 3
Classifier: License :: OSI Approved :: MIT License
Classifier: Operating System :: OS Independent
Requires-Python: >=3.6
License-File: LICENSE
